xcross/__init__.py
xcross/__main__.py
xcross-0.1.7.dist-info/LICENSE
xcross-0.1.7.dist-info/METADATA
xcross-0.1.7.dist-info/WHEEL
xcross-0.1.7.dist-info/entry_points.txt
xcross-0.1.7.dist-info/top_level.txt
xcross-0.1.7.dist-info/RECORD
