Metadata-Version: 2.1
Name: xcross
Version: 0.1.7
Summary: Zero-setup cross compilation.
Home-page: https://github.com/Alexhuszagh/xcross
Author: Alex Huszagh
Author-email: ahuszagh@gmail.com
License: Unlicense
Keywords: compilers cross-compilation embedded
Platform: UNKNOWN
Classifier: Development Status :: 4 - Beta
Classifier: Programming Language :: Python :: 3
Classifier: Programming Language :: Python :: 3.6
Classifier: Programming Language :: Python :: 3.7
Classifier: Programming Language :: Python :: 3.8
Classifier: Programming Language :: Python :: 3.9
Classifier: License :: OSI Approved :: The Unlicense (Unlicense)
Classifier: Topic :: Software Development :: Compilers
Classifier: Topic :: Software Development :: Embedded Systems
Requires-Python: >3.6.0
